LICENSE
MANIFEST.in
README.rst
setup.py
cdk/__init__.py
cdk/b64.py
cdk/to6.py
cdk.egg-info/PKG-INFO
cdk.egg-info/SOURCES.txt
cdk.egg-info/dependency_links.txt
cdk.egg-info/entry_points.txt
cdk.egg-info/requires.txt
cdk.egg-info/top_level.txt
cdk/custom/asciidoc.conf
cdk/custom/deckjs.conf
cdk/custom/html5.conf
cdk/custom/prefs
cdk/custom/sample.asc
cdk/custom/deck.js/extensions/anchor/deck.anchor.js
cdk/custom/deck.js/extensions/breadcrumb/deck.breadcrumb.css
cdk/custom/deck.js/extensions/breadcrumb/deck.breadcrumb.js
cdk/custom/deck.js/extensions/help/deck.help.css
cdk/custom/deck.js/extensions/help/deck.help.js
cdk/custom/deck.js/extensions/quiz/deck.quiz.js
cdk/custom/deck.js/extensions/scrolltop/deck.scrolltop.js
cdk/custom/deck.js/extensions/slidetheme/Makefile
cdk/custom/deck.js/extensions/slidetheme/deck.slidetheme.css
cdk/custom/deck.js/extensions/slidetheme/deck.slidetheme.js
cdk/custom/deck.js/extensions/slidetheme/deck.slidetheme.less
cdk/custom/deck.js/extensions/toc/deck.toc.css
cdk/custom/deck.js/extensions/toc/deck.toc.html
cdk/custom/deck.js/extensions/toc/deck.toc.js
cdk/custom/deck.js/extensions/toc/deck.toc.scss
cdk/custom/deck.js/stylesheets/pygments.css
cdk/custom/deck.js/stylesheets/transition/beamer.css
cdk/custom/deck.js/stylesheets/transition/beamer.scss
cdk/custom/deck.js/stylesheets/transition/fade.css
cdk/custom/deck.js/stylesheets/transition/fade.scss
cdk/custom/deck.js/stylesheets/transition/horizontal-slide.css
cdk/custom/deck.js/stylesheets/transition/horizontal-slide.scss
cdk/custom/deck.js/stylesheets/transition/vertical-slide.css
cdk/custom/deck.js/stylesheets/transition/vertical-slide.scss
cdk/custom/deck.js/themes/plain/plain.css
cdk/custom/deck.js/themes/plain/plain.less
cdk/custom/deck.js/themes/plain/vars.css
cdk/custom/deck.js/themes/plain/vars.less
cdk/custom/deck.js/themes/twitter/Makefile
cdk/custom/deck.js/themes/twitter/b64.py
cdk/custom/deck.js/themes/twitter/twitter-bird-light-bgs.png
cdk/custom/deck.js/themes/twitter/twitter.css
cdk/custom/deck.js/themes/twitter/twitter.less
cdk/custom/deck.js/themes/twitter/vars.css
cdk/custom/deck.js/themes/twitter/vars.less
