Metadata-Version: 1.1
Name: cdk
Version: 1.0.6
Summary: Courseware Developement Kit based on asciidoc and deck.js
Home-page: https://github.com/twitter-university/cdk
Author: Simeon Franklin
Author-email: simeonf@gmail.com
License: 
